ValidPath/__init__.py
ValidPath/WSI/__init__.py
ValidPath/WSI/annotation.py
ValidPath/WSI/patch.py
ValidPath/WSI/reader.py
ValidPath/WSI/readwsi.py
ValidPath/assessment/__init__.py
ValidPath/assessment/annotation.py
ValidPath/assessment/uncertainty.py
ValidPath-0.0.5.dist-info/METADATA
ValidPath-0.0.5.dist-info/WHEEL
ValidPath-0.0.5.dist-info/top_level.txt
ValidPath-0.0.5.dist-info/RECORD
