Metadata-Version: 2.1
Name: ValidPath
Version: 0.0.5
Summary: Processing Digital Pathology Data
Author: Seyed Mostafa Mousavi Kahaki
Author-email: <mousavikahaki@gmail.com>
Keywords: python,whole slide,image,pathology,WSI,medical image
Classifier: Development Status :: 1 - Planning
Classifier: Intended Audience :: Developers
Classifier: Programming Language :: Python :: 3
Classifier: Operating System :: Unix
Classifier: Operating System :: MacOS :: MacOS X
Classifier: Operating System :: Microsoft :: Windows
Requires-Dist: opencv-python
Requires-Dist: pyautogui
Requires-Dist: pyaudio
